calculator/__init__.py
calculator/calculator.py
calculator/history.py
calculator/main.py
calculator/math_functions.py
calculator/validation.py
calculator/styles/__init__.py
calculator/styles/style.qss
calculator/ui/__init__.py
calculator/ui/calculator1_gui.ui
calculator/ui/calculator_gui.py
pyqt5_calculator0_1-0.1.0.dist-info/METADATA
pyqt5_calculator0_1-0.1.0.dist-info/WHEEL
pyqt5_calculator0_1-0.1.0.dist-info/top_level.txt
pyqt5_calculator0_1-0.1.0.dist-info/RECORD
