Metadata-Version: 2.4
Name: pyqt5-calculator0.1
Version: 0.1.0
Summary: Simple PyQt5 calculator application
Home-page: https://github.com/Asasai001/calculator
Author: Arnoldas A.
Author-email: ambrasas.arnoldas@gmail.com
Classifier: Programming Language :: Python :: 3
Classifier: Operating System :: OS Independent
Requires-Python: >=3.7
Requires-Dist: PyQt5
Dynamic: author
Dynamic: author-email
Dynamic: classifier
Dynamic: description
Dynamic: description-content-type
Dynamic: home-page
Dynamic: requires-dist
Dynamic: requires-python
Dynamic: summary
